qpace_suite-0.0.1.dist-info/METADATA
qpace_suite-0.0.1.dist-info/WHEEL
qpace_suite/__init__.py
qpace_suite/_lib.abi3.so
qpace_suite/algoalpha/__init__.py
qpace_suite/algoalpha/adaptive_schaff_trend_cycle.py
qpace_suite/algoalpha/amazing_oscillator.py
qpace_suite/algoalpha/donchain_trend_ranges.py
qpace_suite/algoalpha/exponential_trend.py
qpace_suite/algoalpha/supertrended_rsi.py
qpace_suite/algoalpha/triple_smoothed_signals.py
qpace_suite/jdehorty/__init__.py
qpace_suite/jdehorty/kernel_functions.py
qpace_suite/jdehorty/machine_learning_lorentzian_classification.py
qpace_suite/jdehorty/ml_extensions.py
qpace_suite/jdehorty/nadaraya_watson_envelope.py
qpace_suite/jdehorty/wavetrend_3d.py
qpace_suite-0.0.1.dist-info/RECORD
